cli_app/__init__.py
cli_app/categorical.py
cli_app/data_description.py
cli_app/data_input.py
cli_app/download.py
cli_app/feature_scaling.py
cli_app/imputation.py
cli_app/main.py
Machine_Learning_Preprocess_CLI-1.0.1.dist-info/LICENSE.md
Machine_Learning_Preprocess_CLI-1.0.1.dist-info/METADATA
Machine_Learning_Preprocess_CLI-1.0.1.dist-info/WHEEL
Machine_Learning_Preprocess_CLI-1.0.1.dist-info/dependency_links.txt
Machine_Learning_Preprocess_CLI-1.0.1.dist-info/entry_points.txt
Machine_Learning_Preprocess_CLI-1.0.1.dist-info/top_level.txt
Machine_Learning_Preprocess_CLI-1.0.1.dist-info/RECORD
