Metadata-Version: 2.1
Name: Machine-Learning-Preprocess-CLI
Version: 1.0.1
Summary: A simple commandline app for searching and looking up opensource vulnerabilities
Home-page: https://github.com/princ3raj/Machine_learning_preprocessor_cli
Author: Akshat Das, Prince Raj, Kartik Goel, Saraansh Mishra
Author-email: princ3raj1999@gmail.com
License: MIT
Download-URL: https://github.com/princ3raj/Machine_learning_preprocessor_cli
Platform: UNKNOWN
Classifier: License :: OSI Approved :: MIT License
Classifier: Programming Language :: Python :: 3.7
Classifier: Programming Language :: Python :: 3
Classifier: Programming Language :: Python :: 3.7
Requires-Python: >=2.7
Requires-Dist: joblib (==1.0.1)
Requires-Dist: numpy (==1.21.2)
Requires-Dist: pandas (==1.0.5)
Requires-Dist: python-dateutil (==2.8.2)
Requires-Dist: pytz (==2021.1)
Requires-Dist: scikit-learn (==0.23.1)
Requires-Dist: scipy (==1.7.1)
Requires-Dist: six (==1.16.0)
Requires-Dist: threadpoolctl (==2.2.0)
